{
  "date": "1945",
  "ext": 10,
  "category_local_name": "Briefe an Ulrich Becher ",
  "iiif-manifest": "https:\/\/iiif.ub.unibe.ch\/presentation\/v2.1\/manifest\/ef6c9956-8da4-408c-a5ac-681326a85e8d\/",
  "signature": "",
  "holding_institution": "DEA",
  "title": "Brief",
  "category_global_name": "Briefe an Ulrich Becher, 1912-1990",
  "iiif": "https:\/\/iiif.ub.unibe.ch\/image\/v3\/dsl_dev\/1284072029_00000010.tif\/info.json",
  "prototype": true,
  "links": {
    "culturegraph": "http:\/\/hub.culturegraph.org\/resource\/DNB-1284072029",
    "gnd": "https:\/\/d-nb.info\/1284072029"
  },
  "category": 20100,
  "entry_type": "http:\/\/purl.org\/ontology\/bibo\/Document",
  "key": "(DE-101)1284072029",
  "levels": [  ]
}