{
  "ext": [ "1 Blatt maschinenschriftlicher Durchschlag. Verso: Ulrich Becher an Herrn Nestler, 7.1.70" ],
  "recipient_uri": [ "https:\/\/d-nb.info\/gnd\/138278547" ],
  "category_global_name": "Briefe von Ulrich Becher, 1916-1990",
  "place": [ "Leipzig", "Frankfurt am Main" ],
  "ext_num": -1,
  "creator": [ "Ulrich Becher" ],
  "lang": [  ],
  "date": [ "1970" ],
  "encl": [  ],
  "note": [
    "Briefkopf: für ein paar Tage Hotelpension Arenberg, Wien",
    "Vorliegende Namensform Adressat: Herrn Prof. Dr. Gustav von Manker, Direktor des Volkstheaters in Wien"
  ],
  "signature": "DEA-B-3-1-0017.B.02.0475",
  "title": "Brief",
  "content": [  ],
  "recipient": [ "Gustav Manker" ],
  "creator_uri": [ "https:\/\/d-nb.info\/gnd\/118507958" ],
  "links": {
    "culturegraph": "http:\/\/hub.culturegraph.org\/resource\/DNB-1284849554",
    "gnd": "https:\/\/d-nb.info\/1284849554"
  },
  "type": "letter",
  "category": 20200,
  "key": "(DE-101)1284849554"
}