{
  "ext": [ "18 Blatt maschinenschriftlich, Xerox. Mit Korrekturen" ],
  "category_global_name": "",
  "ext_num": -1,
  "creator": [ "Ulrich Becher" ],
  "lang": [  ],
  "date": [ "1900" ],
  "note": [
    "Reproduktion von: Fragment (d.h. Teilkapitel Boeckl), Korrekturstufe \"3\"",
    "Betrifft: Walter Muschg; Fritz Wotruba"
  ],
  "signature": "DEA-B-3-1-0017.A.01.05.0223",
  "title": "Wotrubas Dohle",
  "content": [  ],
  "creator_uri": [ "https:\/\/d-nb.info\/gnd\/118507958" ],
  "links": {
    "culturegraph": "http:\/\/hub.culturegraph.org\/resource\/DNB-1283998955",
    "gnd": "https:\/\/d-nb.info\/1283998955"
  },
  "type": "work",
  "category": 1099095,
  "key": "(DE-101)1283998955"
}