{
  "ext": [ "42 Blatt maschinenschriftlicher Durchschlag und anderes. Mit Korrekturen" ],
  "category_global_name": "Romane",
  "ext_num": 84,
  "creator": [ "Ulrich Becher" ],
  "lang": [  ],
  "date": [ "1900" ],
  "note": [ "Reproduktion von: Frühe Fassung?, Fragment" ],
  "signature": "DEA-B-3-1-0017.A.01.01.0046",
  "title": "Murmeljagd, [Roman] – Ich warf ihm meine … [Incipit]",
  "content": [  ],
  "creator_uri": [ "https:\/\/d-nb.info\/gnd\/118507958" ],
  "links": {
    "culturegraph": "http:\/\/hub.culturegraph.org\/resource\/DNB-1283944421",
    "gnd": "https:\/\/d-nb.info\/1283944421"
  },
  "type": "work",
  "iiif": "https:\/\/iiif.ub.unibe.ch\/image\/v3\/dsl_dev\/1283944421_00000010.tif\/info.json",
  "category": 10200,
  "key": "(DE-101)1283944421",
  "iiif-manifest": "https:\/\/iiif.ub.unibe.ch\/presentation\/v2.1\/manifest\/9b11bd43-1e39-4dd9-9164-b1e19de9bc50\/"
}