{
  "date": "",
  "ext": 0,
  "category_local_name": "Selbstständige Belegexemplare",
  "iiif-manifest": "",
  "signature": "",
  "holding_institution": "DEA",
  "title": "Konvolut von Zeitschriften-Beiträgen über Ulrich Becher, in Heften",
  "category_global_name": "",
  "iiif": "",
  "prototype": false,
  "links": {
    "culturegraph": "http:\/\/hub.culturegraph.org\/resource\/DNB-1238052770",
    "gnd": "https:\/\/d-nb.info\/1238052770"
  },
  "category": 0,
  "entry_type": "http:\/\/purl.org\/ontology\/bibo\/Series",
  "key": "(DE-101)1238052770",
  "levels": [  ]
}