{
  "ext": [ "1 Bl." ],
  "category_global_name": "",
  "place": [ "Wien" ],
  "ext_num": 0,
  "creator": [ "Becher, Ulrich (1910-1990)" ],
  "lang": [  ],
  "date": [ "1953" ],
  "encl": [  ],
  "note": [ "[Bemerkung] o. D." ],
  "signature": "SLA-UB-D-1-a-09-b",
  "title": "Becher, Ulrich: Nur ein kleiner Dreh. Neues Österreich, Wien",
  "content": [  ],
  "creator_uri": [ "https:\/\/d-nb.info\/gnd\/118507958" ],
  "links": { "helveticArchives":"https:\/\/www.helveticarchives.ch\/archivplansuche.aspx?ID=1535622" },
  "type": "collItem",
  "iiif": "",
  "category": 40100,
  "key": "CH-000015-0-1535622",
  "iiif-manifest": ""
}