{
  "ext": [ "Typoskripte, maschinenschriftlich teilweise mit handschriftlichen Korrekturen, Durchschlag, 3 Blatt" ],
  "category_global_name": "",
  "place": [  ],
  "ext_num": 0,
  "creator": [ "Becher, Martin Roda (1944-)", "Becher, Ulrich (1910-1990)" ],
  "lang": [  ],
  "date": [ "1953" ],
  "encl": [  ],
  "note": [  ],
  "signature": "SLA-UB-C-3-e-2-f-02",
  "title": "Becher, Martin Roda: Vorworte",
  "content": [ "Varianten des Vorwortes" ],
  "creator_uri": [ "https:\/\/d-nb.info\/gnd\/121205207", "https:\/\/d-nb.info\/gnd\/118507958" ],
  "links": { "helveticArchives":"https:\/\/www.helveticarchives.ch\/archivplansuche.aspx?ID=1565633" },
  "type": "lifeDoc",
  "category": 3099093,
  "key": "CH-000015-0-1565633"
}