{
  "ext": [ "" ],
  "category_global_name": "",
  "place": [ "Frankfurt" ],
  "ext_num": 0,
  "creator": [ "Becher, Ulrich (1910-1990)" ],
  "lang": [  ],
  "date": [ "14. Mai 1966" ],
  "encl": [  ],
  "note": [ "[Bemerkung] masch. Anm. \"soll um 3 Seiten erweitert werden\"" ],
  "signature": "SLA-UB-D-1-d-14-b",
  "title": "Becher, Ulrich: Der Gewaltinger. Frankfurter Rundschau, Frankfurt",
  "content": [  ],
  "creator_uri": [ "https:\/\/d-nb.info\/gnd\/118507958" ],
  "links": { "helveticArchives":"https:\/\/www.helveticarchives.ch\/archivplansuche.aspx?ID=1537278" },
  "type": "collItem",
  "iiif": "",
  "category": 40100,
  "key": "CH-000015-0-1537278",
  "iiif-manifest": ""
}