{
  "date": "9. Mai 1961",
  "signature": "SLA-UB-B-4-RUECK-37",
  "holding_institution": "SLA",
  "title": "R체ckerstattungsgespr채che zwischen Hans Gumpert und Richard und Elise Becher, Basel;\nBasel",
  "category": 20400,
  "entry_type": "item",
  "key": "CH-000015-0-1698476",
  "levels": [
    { "'title":"Briefe", "level":1 },
    { "'title":"Briefkonvolute", "level":2 },
    {
      "'title": "R체ckerstattungsgespr채che zwischen Hans Gumpert und Richard und Elise Becher",
      "level": 3
    }
  ]
}