{
  "date": "1. Oktober 1983",
  "ext": 0,
  "iiif-manifest": "",
  "signature": "SLA-UB-B-2-MAU-1",
  "holding_institution": "SLA",
  "title": "Maurer, Beatrice an Becher, Ulrich; Korrespondenz, Magden",
  "category": 20100,
  "entry_type": "item",
  "iiif": "",
  "prototype": false,
  "key": "CH-000015-0-1642086",
  "levels": [
    { "'title":"Briefe", "level":1 },
    { "'title":"Briefe an Ulrich Becher", "level":2 },
    {
      "'title": "Maurer, Beatrice an Becher, Ulrich; Korrespondenz, Buenos Aires; Magden; Surava",
      "level": 3
    }
  ]
}