{
  "date": "3. Februar 1949",
  "ext": 0,
  "category_local_name": "Briefe Dritter",
  "iiif-manifest": "",
  "signature": "SLA-UB-B-3-EISK-LESK-1",
  "holding_institution": "SLA",
  "title": "Eisenberg, Katharina an Leskoschek, Axl; Korrespondenz, Zürich;\nWien",
  "category_global_name": "Briefe Dritter, 1930-1990",
  "iiif": "",
  "prototype": false,
  "links": { "helveticArchives":"https:\/\/www.helveticarchives.ch\/archivplansuche.aspx?ID=1685024" },
  "category": 20300,
  "entry_type": "item",
  "key": "CH-000015-0-1685024",
  "levels": [
    { "'title":"Briefe", "level":1 },
    { "'title":"Briefe Dritter", "level":2 },
    {
      "'title": "Eisenberg, Katharina an Leskoschek, Axl; Korrespondenz, Zürich",
      "level": 3
    }
  ]
}