{
  "ext": [ "21 Belegexemplare" ],
  "category_global_name": "",
  "place": [ "Luzern" ],
  "ext_num": 0,
  "creator": [ "Becher, Ulrich (1910-1990)" ],
  "lang": [  ],
  "date": [ "20. September bis 2. Oktober 1955" ],
  "encl": [  ],
  "note": [ "[Bemerkung] Erzählung in 11 Folgen" ],
  "signature": "SLA-UB-D-1-a-21-b",
  "title": "Becher, Ulrich: Das Blauwolkenhaus. Luzerner Tagblatt, Luzern",
  "content": [  ],
  "creator_uri": [ "https:\/\/d-nb.info\/gnd\/118507958" ],
  "links": { "helveticArchives":"https:\/\/www.helveticarchives.ch\/archivplansuche.aspx?ID=1535713" },
  "type": "collItem",
  "category": 40100,
  "key": "CH-000015-0-1535713"
}