{
  "date": "16. Februar 1979",
  "ext": 0,
  "category_local_name": "Briefe an Ulrich Becher ",
  "iiif-manifest": "",
  "signature": "SLA-UB-B-2-HUBE-1",
  "holding_institution": "SLA",
  "title": "Huber Verlag an Becher, Ulrich; Korrespondenz, Frauenfeld;\nBasel",
  "category_global_name": "Briefe an Ulrich Becher, 1912-1990",
  "iiif": "",
  "prototype": false,
  "links": { "helveticArchives":"https:\/\/www.helveticarchives.ch\/archivplansuche.aspx?ID=1640780" },
  "category": 20100,
  "entry_type": "item",
  "key": "CH-000015-0-1640780",
  "levels": [
    { "'title":"Briefe", "level":1 },
    { "'title":"Briefe an Ulrich Becher", "level":2 },
    { "'title":"Huber Verlag an Becher, Ulrich; Korrespondenz, Frauenfeld", "level":3 }
  ]
}