{
  "category_local_name": "Beiträge über Ulrich Becher in Zeitschriften, Zeitungen etc.",
  "ext": [ "ca. 10 Zeitungsartikel" ],
  "category_global_name": "",
  "place": [  ],
  "ext_num": 0,
  "creator": [  ],
  "lang": [  ],
  "date": [ "1935 bis 1970" ],
  "encl": [  ],
  "note": [  ],
  "signature": "SLA-UB-D-2-d-12",
  "title": "Politik und Zeitgeschehen",
  "content": [ "z.B. zur Niederwerfung Serbiens 1915, Wahl de Gaulles (1967), Chrustschow, etc" ],
  "creator_uri": [  ],
  "links": { "helveticArchives":"https:\/\/www.helveticarchives.ch\/archivplansuche.aspx?ID=1545530" },
  "type": "collItem",
  "holding_institution": "SLA",
  "iiif": "",
  "category": 40200,
  "key": "CH-000015-0-1545530",
  "iiif-manifest": ""
}