{
  "ext": [ "Typoskript, 1 Blatt, paginiert (S. 18), unvollständig, mit handschriftlichen Korrekturen" ],
  "category_global_name": "Erzählungen",
  "ext_num": 0,
  "creator": [ "Becher, Ulrich (1910-1990)" ],
  "lang": [  ],
  "date": [ "" ],
  "note": [  ],
  "signature": "SLA-UB-A-1-f-73-1",
  "title": "Becher, Ulrich: Nachts im Park (Fragment)",
  "content": [ "Ein Junge pfeift nachts im Park und zieht damit den Ärger eines Unbekannten auf sich." ],
  "creator_uri": [ "https:\/\/d-nb.info\/gnd\/118507958" ],
  "links": { "helveticArchives":"https:\/\/www.helveticarchives.ch\/archivplansuche.aspx?ID=1557947" },
  "type": "work",
  "category": 10100,
  "key": "CH-000015-0-1557947"
}