{
  "ext": [ "1 Brief, maschinenschriftlich" ],
  "recipient_uri": [ "https:\/\/d-nb.info\/gnd\/139244077" ],
  "category_global_name": "Briefe Dritter, 1930-1990",
  "place": [ "Locarno-Monti;\nBasel" ],
  "ext_num": 0,
  "creator": [ "Neumann, Robert (1897-1975)" ],
  "lang": [  ],
  "date": [ "31. Dezember 1966" ],
  "encl": [  ],
  "note": [  ],
  "signature": "SLA-UB-B-3-NEUM-BECHD-12",
  "title": "Neumann, Robert an Becher, Dana; Korrespondenz, Locarno-Monti;\nBasel",
  "content": [  ],
  "recipient": [ "Roda Becher, Dana (1909-1992)" ],
  "creator_uri": [ "https:\/\/d-nb.info\/gnd\/118587331" ],
  "links": { "helveticArchives":"https:\/\/www.helveticarchives.ch\/archivplansuche.aspx?ID=1687094" },
  "type": "letter",
  "iiif": "",
  "category": 20300,
  "key": "CH-000015-0-1687094",
  "iiif-manifest": ""
}