{
  "category_local_name": "Kleine Manuskripte und Typoskripte",
  "ext": [ "1 Blatt maschinenschriftlicher Durchschlag. Mit Korrekturen" ],
  "category_global_name": "",
  "ext_num": -1,
  "creator": [ "Ulrich Becher" ],
  "lang": [  ],
  "date": [ "1900" ],
  "note": [
    "Reproduktion von: Frühe Fassung?, Fragment",
    "Titel fingiert (gemäß Benennung des Konvoluts, in dem das Archivale überliefert wurde)",
    "Eigentlicher Titel des Archivales: Der Angriff bei Lupignano"
  ],
  "signature": "DEA-B-3-1-0017.A.01.05.0147",
  "title": "Der obligate Ausfall",
  "content": [  ],
  "creator_uri": [ "https:\/\/d-nb.info\/gnd\/118507958" ],
  "links": {
    "culturegraph": "http:\/\/hub.culturegraph.org\/resource\/DNB-1283984164",
    "gnd": "https:\/\/d-nb.info\/1283984164"
  },
  "type": "work",
  "holding_institution": "DEA",
  "iiif": "",
  "category": 1099095,
  "key": "(DE-101)1283984164",
  "iiif-manifest": ""
}