{
  "category_local_name": "",
  "ext": [ "1 Karte handschriftlich mit Unterschrift. Mit Umschlag" ],
  "wit": [  ],
  "category_global_name": "",
  "place": [ "Leipzig", "Frankfurt am Main" ],
  "ext_num": -1,
  "creator": [ { "name":"Anna Linke", "uri":"https:\/\/d-nb.info\/gnd\/1133575420" } ],
  "lang": [ "Deutsch", "Deutsch Englisch Polnisch" ],
  "date": [ "1961" ],
  "encl": [  ],
  "note": [  ],
  "signature": "DEA-B-3-1-0017.B.01.1087",
  "title": "Anna Linke an Ulrich Becher, 1961",
  "content": [  ],
  "recipient": [ { "name":"Ulrich Becher", "uri":"https:\/\/d-nb.info\/gnd\/118507958" } ],
  "links": {
    "culturegraph": "http:\/\/hub.culturegraph.org\/resource\/DNB-1284200221",
    "gnd": "https:\/\/d-nb.info\/1284200221"
  },
  "wit-info": [  ],
  "type": "letter",
  "holding_institution": "DEA",
  "iiif": "",
  "category": 20100,
  "key": "(DE-101)1284200221",
  "iiif-manifest": ""
}