{
  "category_local_name": "Mechnig, Elfriede an Becher, Ulrich; Korrespondenz, Berlin",
  "ext": [ "1 Karte maschinenschriftlich mit Unterschrift" ],
  "recipient_uri": [ "https:\/\/d-nb.info\/gnd\/118507958" ],
  "category_global_name": "",
  "place": [ "Leipzig", "Frankfurt am Main" ],
  "ext_num": -1,
  "creator": [ "Elfriede Mechnig" ],
  "lang": [  ],
  "date": [ "1959" ],
  "encl": [  ],
  "note": [  ],
  "signature": "SLA-UB-B-2-164",
  "title": "Elfriede Mechnig an Ulrich Becher, 1959",
  "content": [  ],
  "recipient": [ "Ulrich Becher" ],
  "creator_uri": [ "https:\/\/d-nb.info\/gnd\/1026358825" ],
  "links": {
    "culturegraph": "http:\/\/hub.culturegraph.org\/resource\/DNB-1284217280",
    "gnd": "https:\/\/d-nb.info\/1284217280"
  },
  "type": "letter",
  "holding_institution": "DEA",
  "iiif": "",
  "category": 201164,
  "key": "(DE-101)1284217280",
  "iiif-manifest": ""
}