{
  "category_local_name": "",
  "ext": [ "1 Blatt maschinenschriftlich mit Unterschrift (unleserlich)" ],
  "wit": [  ],
  "recipient_uri": [ "https:\/\/d-nb.info\/gnd\/118507958" ],
  "category_global_name": "",
  "place": [ "Leipzig", "Frankfurt am Main" ],
  "ext_num": -1,
  "creator": [ "Sinn und Form" ],
  "lang": [ "Deutsch" ],
  "date": [ "1962" ],
  "encl": [  ],
  "note": [ "Briefkopf: Sinn und Form, Beiträge zur Literatur, Redaktion" ],
  "signature": "DEA-B-3-1-0017.B.01.3368",
  "title": "Sinn und Form an Ulrich Becher, 1962",
  "content": [  ],
  "recipient": [ "Ulrich Becher" ],
  "creator_uri": [  ],
  "links": {
    "culturegraph": "http:\/\/hub.culturegraph.org\/resource\/DNB-1284708713",
    "gnd": "https:\/\/d-nb.info\/1284708713"
  },
  "wit-info": [  ],
  "type": "letter",
  "holding_institution": "DEA",
  "iiif": "",
  "category": 20100,
  "key": "(DE-101)1284708713",
  "iiif-manifest": ""
}