{
  "category_local_name": "",
  "ext": [ "4 Hefte und 1 Blatt = 5 Einheiten Druck und anderes" ],
  "category_global_name": "",
  "place": [ "Leipzig", "Frankfurt am Main" ],
  "ext_num": -1,
  "creator": [  ],
  "lang": [  ],
  "date": [ "" ],
  "encl": [  ],
  "note": [  ],
  "signature": "DEA-B-3-1-0017.D.02.0004",
  "title": "Konvolut von Programmen seines Theaterstücks Der Herr kommt aus Bahia",
  "content": [  ],
  "creator_uri": [  ],
  "links": {
    "culturegraph": "http:\/\/hub.culturegraph.org\/resource\/DNB-1282790668",
    "gnd": "https:\/\/d-nb.info\/1282790668"
  },
  "type": "collItem",
  "holding_institution": "DEA",
  "iiif": "",
  "category": 40230,
  "key": "(DE-101)1282790668",
  "iiif-manifest": ""
}