{
  "category_local_name": "Kleine Manuskripte und Typoskripte",
  "ext": [ "4 Blatt handschriftlich Durchschrift von Dana Becher und anderes" ],
  "category_global_name": "",
  "place": [ "Leipzig", "Frankfurt am Main" ],
  "ext_num": -1,
  "creator": [ "Ulrich Becher" ],
  "lang": [  ],
  "date": [ "1900" ],
  "note": [ "Es handelt sich hierbei um ein fragmentarisches Manuskript-Typoskript mit den Titeln: Kleines orphisches Nocturno bzw. Orphisches Nocturno" ],
  "signature": "DEA-B-3-1-0017.A.01.05.0187",
  "title": "Stammgast im Liliputanercafé - beiliegendes Material",
  "content": [  ],
  "creator_uri": [ "https:\/\/d-nb.info\/gnd\/118507958" ],
  "links": {
    "culturegraph": "http:\/\/hub.culturegraph.org\/resource\/DNB-1283989298",
    "gnd": "https:\/\/d-nb.info\/1283989298"
  },
  "type": "work",
  "holding_institution": "DEA",
  "iiif": "",
  "category": 1099095,
  "key": "(DE-101)1283989298",
  "iiif-manifest": ""
}