{
  "category_local_name": "Kleine Manuskripte und Typoskripte",
  "ext": [ "54 Blatt handschriftlich Durchschrift" ],
  "category_global_name": "",
  "ext_num": -1,
  "creator": [ "" ],
  "lang": [  ],
  "date": [ "1900" ],
  "note": [
    "Reproduktion von: Rohmanuskript",
    "Titel fingiert (gemäß Benennung des Konvoluts, in dem das Archivale überliefert wurde)",
    "Eigentlicher Titel des Archivales: Siff"
  ],
  "signature": "DEA-B-3-1-0017.A.01.05.0067",
  "title": "Hades-Telefonate",
  "content": [  ],
  "creator_uri": [  ],
  "links": {
    "culturegraph": "http:\/\/hub.culturegraph.org\/resource\/DNB-1283966999",
    "gnd": "https:\/\/d-nb.info\/1283966999"
  },
  "type": "work",
  "holding_institution": "DEA",
  "iiif": "",
  "category": 1099095,
  "key": "(DE-101)1283966999",
  "iiif-manifest": ""
}