{
  "category_local_name": "",
  "ext": [ "1 Blatt maschinenschriftlich mit Unterschrift. Im Auftrag geschrieben von Stadtrat Hans Mandl" ],
  "recipient_uri": [ "https:\/\/d-nb.info\/gnd\/118507958" ],
  "category_global_name": "",
  "place": [ "Leipzig", "Frankfurt am Main" ],
  "ext_num": -1,
  "creator": [ "Magistrat der Stadt Wien" ],
  "lang": [  ],
  "date": [ "1954" ],
  "encl": [  ],
  "note": [ "Briefkopf: Magistrat der Stadt Wien, Der Stadtrat der Verwaltungsgruppe III" ],
  "signature": "DEA-B-3-1-0017.B.01.3684",
  "title": "Magistrat der Stadt Wien an Ulrich Becher, 1954",
  "content": [  ],
  "recipient": [ "Ulrich Becher" ],
  "creator_uri": [ "https:\/\/d-nb.info\/gnd\/2078413-2" ],
  "links": {
    "culturegraph": "http:\/\/hub.culturegraph.org\/resource\/DNB-1284752151",
    "gnd": "https:\/\/d-nb.info\/1284752151"
  },
  "type": "letter",
  "holding_institution": "DEA",
  "iiif": "",
  "category": 20100,
  "key": "(DE-101)1284752151",
  "iiif-manifest": ""
}