{
  "category_local_name": "",
  "ext": [ "1 Blatt maschinenschriftlich mit Unterschrift" ],
  "wit": [  ],
  "recipient_uri": [ "https:\/\/d-nb.info\/gnd\/118507958" ],
  "category_global_name": "",
  "place": [ "Leipzig", "Frankfurt am Main" ],
  "ext_num": -1,
  "creator": [ "Franz Horch", "Franz J. Horch Authors' and Publishers' Representative" ],
  "lang": [ "Englisch" ],
  "date": [ "1947" ],
  "encl": [  ],
  "note": [ "Briefkopf: Franz J. Horch, Authors' and Publishers' Representative" ],
  "signature": "DEA-B-3-1-0017.B.01.0804",
  "title": "Franz Horch, Franz J. Horch Authors' and Publishers' Representative an Ulrich Becher, 1947",
  "content": [  ],
  "recipient": [ "Ulrich Becher" ],
  "creator_uri": [ "https:\/\/d-nb.info\/gnd\/116982802" ],
  "links": {
    "culturegraph": "http:\/\/hub.culturegraph.org\/resource\/DNB-1284145492",
    "gnd": "https:\/\/d-nb.info\/1284145492"
  },
  "wit-info": [  ],
  "type": "letter",
  "holding_institution": "DEA",
  "iiif": "",
  "category": 20100,
  "key": "(DE-101)1284145492",
  "iiif-manifest": ""
}