{
  "category_local_name": "Baumgartner, Ilse an Becher Dana; Korrespondenz, Tokyo;\nWien",
  "ext": [ "1 Postkarte, handschriftlich" ],
  "recipient_uri": [ "https:\/\/d-nb.info\/gnd\/139244077" ],
  "category_global_name": "",
  "place": [ "Nagoya;\nBasel" ],
  "ext_num": 0,
  "creator": [ "Baumgartner, Ilse (20. Jh.)" ],
  "lang": [  ],
  "date": [ "31. August 1983" ],
  "encl": [  ],
  "note": [  ],
  "signature": "SLA-UB-B-3-BAUM-BECHD-2",
  "title": "Baumgartner, Ilse an Becher Dana; Korrespondenz, Nagoya;\nBasel",
  "content": [  ],
  "recipient": [ "Roda Becher, Dana (1909-1992)" ],
  "creator_uri": [  ],
  "links": { "helveticArchives":"https:\/\/www.helveticarchives.ch\/archivplansuche.aspx?ID=1673181" },
  "type": "letter",
  "holding_institution": "SLA",
  "iiif": "",
  "category": 203268,
  "key": "CH-000015-0-1673181",
  "iiif-manifest": ""
}