{
  "category_local_name": "",
  "ext": [ "1 Bl. (2 Ex)" ],
  "wit": [  ],
  "category_global_name": "",
  "place": [  ],
  "ext_num": 0,
  "creator": [ { "name":"Becher, Ulrich (1910-1990)", "uri":"https:\/\/d-nb.info\/gnd\/118507958" } ],
  "lang": [ "Deutsch" ],
  "date": [ "15. Oktober 1953" ],
  "encl": [  ],
  "note": [ "[Bemerkung] S. 7, Neue Zeitung Berlin, Nr. 241" ],
  "signature": "SLA-UB-D-1-a-12-a",
  "title": "Becher, Ulrich: Ophelia in der Schenke. Neue Zeitung, Berlin",
  "content": [  ],
  "links": { "helveticArchives":"https:\/\/www.helveticarchives.ch\/archivplansuche.aspx?ID=1535646" },
  "wit-info": [  ],
  "type": "collItem",
  "holding_institution": "SLA",
  "iiif": "",
  "category": 40110,
  "key": "CH-000015-0-1535646",
  "iiif-manifest": ""
}