{
  "category_local_name": "",
  "ext": [ "Manuskript, 15 Blatt Kopierbuch (restl. Blatt unbeschrieben), paginiert + 15 Blatt Kopierblätter Handschrift Dana" ],
  "wit": [  ],
  "category_global_name": "",
  "place": [  ],
  "ext_num": 0,
  "creator": [ "Becher, Ulrich (1910-1990)" ],
  "lang": [ "Deutsch" ],
  "date": [ "1970 bis 1990" ],
  "note": [ "[Datierung] grob geschätzt" ],
  "signature": "SLA-UB-A-1-g-1-3",
  "title": "Becher, Ulrich: Hades-Telefonate: Schluss Hadesgespräche",
  "content": [ "Erhalt des Parte-Zettels Franz Futterknechts Tod durch Wotrubas Assistenten Franz Hilkesberger. Mitte August 1975 ruft Becher Wotruba an, um den gemeinsamen Venedig-Urlaub zu planen, aber anstelle des Bildhauers ist nur das Krächzen der Hausdohle am anderen Ende der Leitung zu vernehmen. Kurz darauf liest Dana von Wotrubas plötzlichem Tod in der Zeitung. 1976 Antreffen des Wotruba-Schülers Hans Kuckelhauser in Wien, der bestätigt, dass Koko auf Bechers Anruf nach Wotrubas Tod geantwortet haben muss, da er nach der Beerdigung den Hörer abgehoben vorfand." ],
  "creator_uri": [ "https:\/\/d-nb.info\/gnd\/118507958" ],
  "links": { "helveticArchives":"https:\/\/www.helveticarchives.ch\/archivplansuche.aspx?ID=1557969" },
  "wit-info": [  ],
  "type": "work",
  "holding_institution": "SLA",
  "iiif": "",
  "category": 10170,
  "key": "CH-000015-0-1557969",
  "iiif-manifest": ""
}