{
  "category_local_name": "Lyrik",
  "ext": [ "Typoskript, 2 Blatt, vollständig" ],
  "category_global_name": "",
  "place": [  ],
  "ext_num": 0,
  "creator": [ "Becher, Ulrich (1910-1990)" ],
  "lang": [  ],
  "date": [ "1940" ],
  "note": [ "[Bemerkung] Türkis gedruckt, 13 Verse, auf Blatt 2 zusätzlich Gedicht \"Trunkener Spruch\"." ],
  "signature": "SLA-UB-A-3-b-3-3",
  "title": "Becher, Ulrich: Ein Bauer denkt an seinen Pudel",
  "content": [  ],
  "creator_uri": [ "https:\/\/d-nb.info\/gnd\/118507958" ],
  "links": { "helveticArchives":"https:\/\/www.helveticarchives.ch\/archivplansuche.aspx?ID=1558159" },
  "type": "work",
  "holding_institution": "SLA",
  "iiif": "",
  "category": 10300,
  "key": "CH-000015-0-1558159",
  "iiif-manifest": ""
}