{
  "category_local_name": "Dramen",
  "ext": [ "1 braune Mappe mit Aufkleber des Felix Bloch Erben-Verlags" ],
  "category_global_name": "",
  "place": [  ],
  "ext_num": 0,
  "creator": [ "Becher, Ulrich (1910-1990)" ],
  "lang": [  ],
  "date": [ "1949 bis 1954" ],
  "note": [  ],
  "signature": "SLA-UB-A-4-g-3-1",
  "title": "Becher, Ulrich: Mademoiselle Löwenzorn. Umschlagmappe",
  "content": [  ],
  "creator_uri": [ "https:\/\/d-nb.info\/gnd\/118507958" ],
  "links": { "helveticArchives":"https:\/\/www.helveticarchives.ch\/archivplansuche.aspx?ID=1558627" },
  "type": "work",
  "holding_institution": "SLA",
  "iiif": "",
  "category": 10400,
  "key": "CH-000015-0-1558627",
  "iiif-manifest": ""
}