{
  "category_local_name": "",
  "ext": [ "Typoskript Durchschlag, 2 Blatt, unvollständig" ],
  "wit": [  ],
  "date_reg": [ "1936-03-23" ],
  "category_global_name": "",
  "place": [  ],
  "ext_num": 0,
  "creator": [ { "name":"Becher, Ulrich (1910-1990)", "uri":"https:\/\/d-nb.info\/gnd\/118507958" } ],
  "lang": [ "Deutsch" ],
  "date": [ "23. März 1936" ],
  "note": [ "[Biblio] Europa, Nr. 13 (18.03.1936). Nachgedruckt in: Deutsche Volkszeitung (Prag-Paris-Basel), I, Nr. 4 (12.04.1936, S. 7; und in: Mitteilungen der Deutschen Freiheitsbibliothek. Das Freie Deutschland (Paris), Nr. 12 (01.05.1936), S. 12-21. vollständiges Typoskript in: Kleines Mutter-Lesebuch" ],
  "signature": "SLA-UB-A-6-a-1-1",
  "title": "Becher, Ulrich: Einigt euch um Gottes Willen. Aufruf an die Christen und Sozialisten des Abendlandes",
  "content": [ "Plädoyer an die Christen und Sozialisten, sich zu einigen, und gemeinsam gegen den sich bereits androhenden Weltkrieganzukämpfen." ],
  "links": { "helveticArchives":"https:\/\/www.helveticarchives.ch\/archivplansuche.aspx?ID=1558684" },
  "wit-info": [  ],
  "type": "work",
  "holding_institution": "SLA",
  "iiif": "",
  "category": 10610,
  "key": "CH-000015-0-1558684",
  "iiif-manifest": ""
}