{
  "category_local_name": "",
  "ext": [ "Typoskript Durchschlag, 8 Blatt, paginiert" ],
  "wit": [  ],
  "category_global_name": "",
  "place": [  ],
  "ext_num": 0,
  "creator": [ { "name":"Becher, Ulrich (1910-1990)", "uri":"https:\/\/d-nb.info\/gnd\/118507958" } ],
  "lang": [ "Deutsch" ],
  "date": [ "24. März 1954" ],
  "note": [ "[Bemerkung] Vermerk: Filmaufbau GmbH Göttingen." ],
  "signature": "SLA-UB-A-4-e-3-1",
  "title": "Becher, Ulrich: Feuerwasser. Filmexposé",
  "content": [  ],
  "links": { "helveticArchives":"https:\/\/www.helveticarchives.ch\/archivplansuche.aspx?ID=1558596" },
  "wit-info": [  ],
  "type": "work",
  "holding_institution": "SLA",
  "iiif": "",
  "category": 10450,
  "key": "CH-000015-0-1558596",
  "iiif-manifest": ""
}