{
  "category_local_name": "",
  "ext": [ "1 Zettel" ],
  "category_global_name": "",
  "place": [  ],
  "ext_num": 0,
  "creator": [  ],
  "lang": [  ],
  "date": [ "" ],
  "note": [ "[Bemerkung] Tusche auf Papier, Rückseite Rechnung Kurhaus Rigiblick" ],
  "signature": "SLA-UB-A-8-a-66-1",
  "title": "Becher, Ulrich: Drei Schweizer Bürger beim Fussballmätsch",
  "content": [ "3 Karikaturköpfe" ],
  "creator_uri": [  ],
  "links": { "helveticArchives":"https:\/\/www.helveticarchives.ch\/archivplansuche.aspx?ID=1558978" },
  "type": "work",
  "holding_institution": "SLA",
  "iiif": "",
  "category": 10810,
  "key": "CH-000015-0-1558978",
  "iiif-manifest": ""
}