{
  "category_local_name": "La Page Internationale an Becher, Ulrich; Korrespondenz, Paris",
  "ext": [ "1 Brief, maschinenschriftlich" ],
  "recipient_uri": [ "https:\/\/d-nb.info\/gnd\/118507958" ],
  "category_global_name": "",
  "place": [ "Paris;\nBasel" ],
  "ext_num": 0,
  "creator": [ "Grautoff, Uta" ],
  "lang": [  ],
  "date": [ "10. August 1956" ],
  "encl": [  ],
  "note": [  ],
  "signature": "SLA-UB-B-2-LAP-1",
  "title": "La Page Internationale an Becher, Ulrich; Korrespondenz, Paris;\nBasel",
  "content": [  ],
  "recipient": [ "Becher, Ulrich (1910-1990)" ],
  "creator_uri": [  ],
  "links": { "helveticArchives":"https:\/\/www.helveticarchives.ch\/archivplansuche.aspx?ID=1640823" },
  "type": "letter",
  "holding_institution": "SLA",
  "iiif": "",
  "category": 201143,
  "key": "CH-000015-0-1640823",
  "iiif-manifest": ""
}