{
  "category_local_name": "",
  "ext": [ "1 Brief, maschinenschriftlich" ],
  "wit": [  ],
  "category_global_name": "",
  "place": [ "Basel (Stadt); Basel-Stadt", "München" ],
  "ext_num": 0,
  "creator": [ { "name":"Weismann, Willi (1909-1983)", "uri":"https:\/\/d-nb.info\/gnd\/117287490" } ],
  "lang": [ "Deutsch" ],
  "date": [ "19. Februar 1970" ],
  "encl": [  ],
  "note": [ "[Bemerkung] Briefpapier des Parabel Verlags" ],
  "signature": "SLA-UB-B-2-WEIS-2",
  "title": "Weismann, Willi an Becher, Ulrich; Korrespondenz, München;\nBasel",
  "content": [  ],
  "recipient": [ { "name":"Becher, Ulrich (1910-1990)", "uri":"https:\/\/d-nb.info\/gnd\/118507958" } ],
  "links": { "helveticArchives":"https:\/\/www.helveticarchives.ch\/archivplansuche.aspx?ID=1644565" },
  "wit-info": [  ],
  "type": "letter",
  "holding_institution": "SLA",
  "iiif": "",
  "category": 201044,
  "key": "CH-000015-0-1644565",
  "iiif-manifest": ""
}