{
  "category_local_name": "",
  "ext": [ "1 Blatt, signiert" ],
  "wit": [  ],
  "category_global_name": "",
  "place": [  ],
  "ext_num": 0,
  "creator": [  ],
  "lang": [ "Deutsch" ],
  "date": [ "" ],
  "note": [ "[Bemerkung] Lithographie auf festes Papier geklebt\n" ],
  "signature": "SLA-UB-A-8-b-4-1",
  "title": "Becher, Ulrich: Jesusfigur",
  "content": [ "Gekreuzigte Jesusfigur in Berglandschaft" ],
  "links": { "helveticArchives":"https:\/\/www.helveticarchives.ch\/archivplansuche.aspx?ID=1559041" },
  "wit-info": [  ],
  "type": "work",
  "holding_institution": "SLA",
  "iiif": "",
  "category": 10820,
  "key": "CH-000015-0-1559041",
  "iiif-manifest": ""
}