{
  "category_local_name": "",
  "ext": [ "1 Karte, handschriftlich" ],
  "wit": [  ],
  "recipient_uri": [ "https:\/\/d-nb.info\/gnd\/118507958" ],
  "category_global_name": "",
  "place": [ "Huntington, NY", "Basel (Stadt); Basel-Stadt" ],
  "ext_num": 0,
  "creator": [ "Grosz, George (1893-1959)" ],
  "lang": [ "Deutsch" ],
  "date": [ "18. Juni 1958" ],
  "encl": [  ],
  "note": [  ],
  "signature": "SLA-UB-B-2-GRO-52",
  "title": "Grosz, George an Becher, Ulrich; Korrespondenz, Huntington (New York);\nBasel",
  "content": [  ],
  "recipient": [ "Becher, Ulrich (1910-1990)" ],
  "creator_uri": [ "https:\/\/d-nb.info\/gnd\/118542672" ],
  "links": { "helveticArchives":"https:\/\/www.helveticarchives.ch\/archivplansuche.aspx?ID=1640334" },
  "wit-info": [  ],
  "type": "letter",
  "holding_institution": "SLA",
  "iiif": "",
  "category": 201016,
  "key": "CH-000015-0-1640334",
  "iiif-manifest": ""
}