{
  "category_local_name": "",
  "ext": [ "3 Zeitungsartikel (Kopien)" ],
  "wit": [  ],
  "date_reg": [ "1972-05-09" ],
  "category_global_name": "",
  "place": [  ],
  "ext_num": 0,
  "creator": [  ],
  "lang": [ "Deutsch" ],
  "date": [ "9. Mai bis 27. Oktober 1972" ],
  "encl": [  ],
  "note": [ "[Bemerkung] verschiedene Artikel in den Basler Nachrichten, Basler National-Zeitung, Berner Tageblatt" ],
  "signature": "SLA-UB-D-2-b-13",
  "title": "Lesungen 1972, Basel",
  "content": [ "3 Artikel zu Bechers Lesungen im Literarischen Forum Basel und auf Einladung des Benziger Verlags im Zähriger Forum" ],
  "links": { "helveticArchives":"https:\/\/www.helveticarchives.ch\/archivplansuche.aspx?ID=1538455" },
  "wit-info": [  ],
  "type": "collItem",
  "holding_institution": "SLA",
  "iiif": "",
  "category": 40220,
  "key": "CH-000015-0-1538455",
  "iiif-manifest": ""
}